[
    {
        "id" : "1",
        "title" : "Asas",
        "description" : "hakshdkjahkjskadf",
        "developer" : "jdlaskjd",
        "release_year" : "kalskjd",
        "classification" : "dalsd",
        "image" : "dals"
    },{
        "id" : "2",
        "title" : "Asas",
        "description" : "hakshdkjahkjskadf",
        "developer" : "jdlaskjd",
        "release_year" : "kalskjd",
        "classification" : "dalsd",
        "image" : "dals"
    },{
        "id" : "3",
        "title" : "Asas",
        "description" : "hakshdkjahkjskadf",
        "developer" : "jdlaskjd",
        "release_year" : "kalskjd",
        "classification" : "dalsd",
        "image" : "dals"
    }
]